imgtag/__init__.py
imgtag/core.py
imgtag-0.1.1.dist-info/LICENSE
imgtag-0.1.1.dist-info/METADATA
imgtag-0.1.1.dist-info/WHEEL
imgtag-0.1.1.dist-info/top_level.txt
imgtag-0.1.1.dist-info/RECORD
